MarketGym/Constants.py
MarketGym/Env.py
MarketGym/StonkDataLib.py
MarketGym/TradierLib.py
MarketGym/Types.py
MarketGym/utils.py
MarketGym-0.1.2.dist-info/LICENSE.txt
MarketGym-0.1.2.dist-info/METADATA
MarketGym-0.1.2.dist-info/WHEEL
MarketGym-0.1.2.dist-info/top_level.txt
MarketGym-0.1.2.dist-info/RECORD
